pystk/README.md
pystk/__init__.py
pystk/__init__.pyc
pystk/check_url_format.py
pystk/convert_ip2num.py
pystk/convert_ip2num.pyc
pystk/convert_pb2ckpt.py
pystk/date_convertor.py
pystk/keras2tensorflow.py
pystk/config/__init__.py
pystk/config/__init__.pyc
pystk/config/output_log.py
pystk/config/output_log.pyc
pystk-0.1.0a1.dist-info/METADATA
pystk-0.1.0a1.dist-info/RECORD
pystk-0.1.0a1.dist-info/WHEEL
pystk-0.1.0a1.dist-info/top_level.txt
