Metadata-Version: 2.1
Name: pystk
Version: 0.1.0a1
Summary: Python Small Toolkit, containing convenient tools.
Home-page: https://github.com/AxsPlayer/Tool_toolkit
Author: AxsPlayer
Author-email: axsplyer@126.com
Maintainer: AxsPlayer
Maintainer-email: axsplyer@126.com
License: UNKNOWN
Download-URL: https://github.com/AxsPlayer/Tool_toolkit/tarball/2018-07-25
Platform: UNKNOWN
Classifier: License :: OSI Approved :: Apache Software License
Classifier: Programming Language :: Python :: 2.7
Requires-Python: >=2.6, !=3.*
Requires-Dist: keras (>=2.1.6)
Requires-Dist: line-profiler (>=2.1.2)
Requires-Dist: tensorflow (>=1.4.0)
